cabot_check_sslcert/__init__.py
cabot_check_sslcert/models.py
cabot_check_sslcert/urls.py
cabot_check_sslcert/views.py
cabot_check_sslcert/migrations/0001_initial.py
cabot_check_sslcert/migrations/0002_add_field_cn.py
cabot_check_sslcert/migrations/__init__.py
cabot_check_sslcert-0.1.11.dist-info/DESCRIPTION.rst
cabot_check_sslcert-0.1.11.dist-info/METADATA
cabot_check_sslcert-0.1.11.dist-info/RECORD
cabot_check_sslcert-0.1.11.dist-info/WHEEL
cabot_check_sslcert-0.1.11.dist-info/metadata.json
cabot_check_sslcert-0.1.11.dist-info/top_level.txt
