Metadata-Version: 2.0
Name: cabot-check-sslcert
Version: 0.1.11
Summary: A SSL certificat check plugin for Cabot
Home-page: https://github.com/decryptus/cabot-check-sslcert
Author: Adrien DELLE CAVE
Author-email: pypi@doowan.net
License: UNKNOWN
Platform: UNKNOWN
